clonedetective/__init__.py
clonedetective/_nbdev.py
clonedetective/clone_analysis.py
clonedetective/clone_counters.py
clonedetective/utils.py
clonedetective-0.0.3.dist-info/LICENSE
clonedetective-0.0.3.dist-info/METADATA
clonedetective-0.0.3.dist-info/WHEEL
clonedetective-0.0.3.dist-info/entry_points.txt
clonedetective-0.0.3.dist-info/top_level.txt
clonedetective-0.0.3.dist-info/RECORD
