Metadata-Version: 2.1
Name: clonedetective
Version: 0.0.3
Summary: A python package for the scalable analysis of fluorescent imaging data from lineage tracing experiments.
Home-page: https://github.com/morriso1/clonedetective/tree/master/
Author: Otto Morris
Author-email: ottomorris@gmail.com
License: Apache Software License 2.0
Keywords: microscopy,image analysis,cell proliferation,cell differentiation,lineage tracing
Platform: UNKNOWN
Classifier: Development Status :: 3 - Alpha
Classifier: Intended Audience :: Science/Research
Classifier: Natural Language :: English
Classifier: Programming Language :: Python :: 3.7
Classifier: Programming Language :: Python :: 3.8
Classifier: License :: OSI Approved :: Apache Software License
Requires-Python: >=3.7
Requires-Dist: pip
Requires-Dist: packaging
Requires-Dist: xarray
Requires-Dist: dask[dataframe]
Requires-Dist: dask[array]
Requires-Dist: dask[distributed]
Requires-Dist: netCDF4
Requires-Dist: bottleneck
Requires-Dist: scipy
Requires-Dist: scikit-image
Requires-Dist: dask-image
Requires-Dist: seaborn
Requires-Dist: numba
Requires-Dist: pyopencl (==2020.3.1)
Requires-Dist: pyclesperanto-prototype
Provides-Extra: dev
